ensemble_regressor_by_mgolec/__init__.py
ensemble_regressor_by_mgolec/ensemble_regressor.py
ensemble_regressor_by_mgolec/regressor.py
ensemble_regressor_by_mgolec-0.1.0.dist-info/LICENSE
ensemble_regressor_by_mgolec-0.1.0.dist-info/METADATA
ensemble_regressor_by_mgolec-0.1.0.dist-info/WHEEL
ensemble_regressor_by_mgolec-0.1.0.dist-info/RECORD
