Metadata-Version: 2.1
Name: ensemble_regressor_by_mgolec
Version: 0.1.0
Summary: A Python package for an ensemble regressor combining multiple regression models.
License: MIT
Author: mgolec
Requires-Python: >=3.9,<4.0
Classifier: License :: OSI Approved :: MIT License
Classifier: Programming Language :: Python :: 3
Classifier: Programming Language :: Python :: 3.9
Classifier: Programming Language :: Python :: 3.10
Classifier: Programming Language :: Python :: 3.11
Classifier: Programming Language :: Python :: 3.12
Requires-Dist: numpy (>=1.21,<2.0)
Requires-Dist: scikit-learn (>=1.0,<2.0)
